{"cameraMode":{"drawMode":0,"name":"Shaded","section":"Shading Mode"},"sceneLighting":true,"audioPlay":false,"sceneViewState":{"showFog":true,"showMaterialUpdate":false,"showSkybox":true,"showFlares":true,"showImageEffects":true,"showParticleSystems":true},"in2DMode":false,"pivot":{"x":349.3293762207031,"y":239.9395751953125,"z":29.319438934326173},"rotation":{"x":0.04348351061344147,"y":-0.011988436803221703,"z":0.000521802983712405,"w":0.9989827871322632},"size":233.8832550048828,"orthographic":false}